[
    {
        "name": "ようこそ",
        "path": "/guide",
        "markdown": "/playguide-markdown/welcome.md",
        "isContent": true,
        "isHidden": false
    },
    {
        "name": "よくあるご質問",
        "path": "/faq",
        "markdown": "/faq-markdown/faq.md",
        "isContent": true,
        "isHidden": false
    },
    {
        "name": "基本システム",
        "isContent": false,
        "contents": [
            {
                "name": "GUIメニュー",
                "path": "/guide/guimenu",
                "markdown": "/playguide-markdown/war.md",
                "isHidden": false
            },
            {
                "name": "ワールド",
                "path": "/guide/world",
                "markdown": "/playguide-markdown/world.md",
                "isHidden": false
            },
            {
                "name": "クレジット",
                "path": "/guide/currency",
                "markdown": "/playguide-markdown/currency.md",
                "isHidden": false
            },
            {
                "name": "デイリークエスト",
                "path": "/guide/dailyquest",
                "markdown": "/playguide-markdown/dailyquest.md",
                "isHidden": false
            },
            {
                "name": "アドベンチャーチェスト",
                "path": "/guide/adventurechest",
                "markdown": "/playguide-markdown/adventurechest.md",
                "isHidden": false
            },
            {
                "name": "チェストショップ",
                "path": "/guide/chestshop",
                "markdown": "/playguide-markdown/chestshop.md",
                "isHidden": false
            },
            {
                "name": "コンバットログ",
                "path": "/guide/combatlog",
                "markdown": "/playguide-markdown/combatlog.md",
                "isHidden": false
            }
        ]
    },
    {
        "name": "国家",
        "isContent": false,
        "contents": [
            {
                "name": "国家の作り方",
                "path": "/guide/nation",
                "markdown": "/playguide-markdown/nation.md",
                "isHidden": false
            },
            {
                "name": "国家通貨",
                "path": "/guide/nationcurrency",
                "markdown": "/playguide-markdown/nationcurrency.md",
                "isHidden": false
            },
            {
                "name": "役職",
                "path": "/guide/position",
                "markdown": "/playguide-markdown/position.md",
                "isHidden": false
            },
            {
                "name": "領地",
                "path": "/guide/territory",
                "markdown": "/playguide-markdown/territory.md",
                "isHidden": false
            },
            {
                "name": "同盟",
                "path": "/guide/territory",
                "markdown": "/playguide-markdown/alliance.md",
                "isHidden": false
            },
            {
                "name": "保護と販売",
                "path": "/guide/territory",
                "markdown": "/playguide-markdown/alliance.md",
                "isHidden": false
            }
        ]
    },
    {
        "name": "戦争",
        "isContent": false,
        "contents": [
            {
                "name": "戦争の始め方",
                "path": "/guide/war",
                "markdown": "/playguide-markdown/war.md",
                "isHidden": false
           },
            {
                "name": "ネクサス",
                "path": "/guide/nexus",
                "markdown": "/playguide-markdown/war.md",
                "isHidden": false
           },
            {
                "name": "猶予期間",
                "path": "/guide/grace",
                "markdown": "/playguide-markdown/grace.md",
                "isHidden": false
           },
            {
                "name": "領地の奪取",
                "path": "/guide/take",
                "markdown": "/playguide-markdown/take.md",
                "isHidden": false
           },
            {
                "name": "ロールバック",
                "path": "/guide/rollback",
                "markdown": "/playguide-markdown/rollback.md",
                "isHidden": false
            },
            {
                "name": "賠償金",
                "path": "/guide/reparations",
                "markdown": "/playguide-markdown/compensation.md",
                "isHidden": false
            }
        ]
    },
    {
        "name": "その他",
        "isContent": false,
        "contents": [
            {
                "name": "有償ランク",
                "path": "/guide/rank",
                "markdown": "/playguide-markdown/rank.md",
                "isHidden": false
            },
            {
                "name": "コマンド",
                "path": "/guide/command",
                "markdown": "/playguide-markdown/command.md",
                "isHidden": false
            },
            {
                "name": "世界マップ",
                "path": "/guide/dynmap",
                "markdown": "/playguide-markdown/dynmap.md",
                "isHidden": false
            }
        ]
    }
]
